dynamic_pytables_where_condition.py
dynamic_pytables_where_condition-1.1.1.dist-info/DESCRIPTION.rst
dynamic_pytables_where_condition-1.1.1.dist-info/METADATA
dynamic_pytables_where_condition-1.1.1.dist-info/RECORD
dynamic_pytables_where_condition-1.1.1.dist-info/WHEEL
dynamic_pytables_where_condition-1.1.1.dist-info/metadata.json
dynamic_pytables_where_condition-1.1.1.dist-info/top_level.txt
