Metadata-Version: 2.0
Name: dynamic-pytables-where-condition
Version: 1.1.1
Summary: Python library that dynamically constructs a PyTables where condition from the supplied keyword arguments.
Home-page: https://github.com/petarmaric/dynamic_pytables_where_condition
Author: Petar Maric
Author-email: petarmaric@uns.ac.rs
License: BSD
Platform: any
Classifier: Development Status :: 5 - Production/Stable
Classifier: Intended Audience :: Developers
Classifier: Intended Audience :: Science/Research
Classifier: License :: OSI Approved :: BSD License
Classifier: Operating System :: OS Independent
Classifier: Programming Language :: Python :: 2.7
Classifier: Topic :: Database
Classifier: Topic :: Scientific/Engineering
Classifier: Topic :: Scientific/Engineering :: Physics
